[
  {
    "type": "mapgen",
    "om_terrain": "3storyD_first",
    "weight": 250,
    "method": "json",
    "object": {
      "fill_ter": "t_floor",
      "rows": [
        "#############W##########",
        "#############W##########",
        "#==w==#######WWWWWW#####",
        "#=<<<=######==w=++=w==##",
        "#w   ===ww===p      p=##",
        "#=                   =##",
        "#===----------    ====##",
        "###=d  d|s   |b   =#####",
        "###=-++-|    |b   w#####",
        "###=   d|&   |b   =#####",
        "###w    |--+--    w#####",
        "###w  BB|n        =#####",
        "###w  BB|n   A    88####",
        "###=c   |b   A    N8####",
        "###=D   +         88####",
        "###==ww==      --+=====#",
        "#######>=  TT  |T    C=#",
        "########w  TT  |c    C=#",
        "########+  TT  C     o=#",
        "########+  TT  C     sw#",
        "########=  TT  |     C=#",
        "########=      |RRUUUU=#",
        "########===========ww==#",
        "########################"
      ],
      "palettes": [ "multistory_house", "ground_level" ]
    }
  }
]
