[
  {
    "type": "mapgen",
    "method": "json",
    "om_terrain": "dump",
    "weight": 100,
    "object": {
      "rows": [
        "          ....          ",
        "          ....          ",
        " |||||||||....||||||||| ",
        " |....................| ",
        " |&&&&&&&&&&&&&&&&&&&&| ",
        " |&&&&&&&&&&&&&&&&&&&&| ",
        " |&&&&&&&&&&&&&&&&&&&&| ",
        " |&&&&&&&&&&&&&&&&&&&&| ",
        " |&&&^^^^^^^^^^^^^^&&&| ",
        " |^^^^^^^^^^^^^^^^^^^^| ",
        " |^^^^^^^^^^^^^^^^^^^^| ",
        " |^^^^^^^^^^^^^^^^^^^^| ",
        " |^^^^^^^^^^^^^^^^^^^^| ",
        " |^^^^^^^^^^^^^^^^^^^^| ",
        " |^^^^^^^^^^^^^^^^^^^^| ",
        " |^^^^^^^^^^^^^^^^^^^^| ",
        " |^^^^^^^^^^^^^^^^^^^^| ",
        " |^^^^^^^^^^^^^^^^^^^^| ",
        " |^^^^^^^^^^^^^^^^^^^^| ",
        " |^^^^^^^^^^^^^^^^^^^^| ",
        " |^^^^^^^^^^^^^^^^^^^^| ",
        " |^^^^^^^^^^^^^^^^^^^^| ",
        " |||||||||||||||||||||| ",
        "                        "
      ],
      "palettes": [ "dump_palette" ],
      "place_signs": [ { "signage": "<city> Dump", "x": 9, "y": 2 }, { "signage": "<city> Dump", "x": 14, "y": 2 } ]
    }
  },
  {
    "type": "mapgen",
    "method": "json",
    "om_terrain": "dump",
    "weight": 100,
    "object": {
      "rows": [
        "         ......         ",
        "         ......         ",
        " ||||||||......|||||||| ",
        " |....................| ",
        " |....................| ",
        " |....................| ",
        " |....................| ",
        " |....................| ",
        " |....................| ",
        " |....................| ",
        " |&&&&&&&&&&&&&&&&&&&&| ",
        " |&&&&&&&&&&&&&&&&&&&&| ",
        " |&&&&&&&&&&&&&&&&&&&&| ",
        " |^^^^^^^^^^^^^^^^^^^^| ",
        " |^^^^^^^^^^^^^^^^^^^^| ",
        " |^^^^^^^^^^^^^^^^^^^^| ",
        " |^^^^^^^^^^^^^^^^^^^^| ",
        " |^^^^^^^^^^^^^^^^^^^^| ",
        " |^^^^^^^^^^^^^^^^^^^^| ",
        " |^^^^^^^^^^^^^^^^^^^^| ",
        " |^^^^^^^^^^^^^^^^^^^^| ",
        " |^^^^^^^^^^^^^^^^^^^^| ",
        " |||||||||||||||||||||| ",
        "                        "
      ],
      "palettes": [ "dump_palette" ],
      "place_signs": [ { "signage": "<city> Dump", "x": 8, "y": 2 }, { "signage": "<city> Dump", "x": 15, "y": 2 } ]
    }
  },
  {
    "type": "mapgen",
    "method": "json",
    "om_terrain": "dump",
    "weight": 100,
    "object": {
      "rows": [
        "         ______         ",
        "      ___PPPPPP___      ",
        "    __PPPPPPPPPPPP__    ",
        "   _PPPPPPPPPPPPPPPP_   ",
        "  _PPPPPPPPPPPPPPPPPP_  ",
        "  _PPPPPPPP&&PPPPPPPP__ ",
        " _PPPPPPP&&&&&&PPPPPPP_ ",
        " _PPPPP&&&&&&&&&&PPPPP_ ",
        " _PPPPP&&&&&&&&&&PPPPP_ ",
        "_PPPPP&&&&&^^&&&&&PPPPP_",
        "_PPPPP&&&&^^^^&&&&PPPPP_",
        "_PPPP&&&&^^^^^^&&&&PPPP_",
        "_PPPP&&&&^^^^^^&&&&PPPP_",
        "_PPPPP&&&&^^^^&&&&PPPPP_",
        "_PPPPP&&&&&^^&&&&&PPPPP_",
        " _PPPPP&&&&&&&&&&PPPPP_ ",
        " _PPPPP&&&&&&&&&&PPPPP_ ",
        " _PPPPPPP&&&&&&PPPPPPP_ ",
        "  _PPPPPPPP&&PPPPPPPP_  ",
        "  _PPPPPPPPPPPPPPPPPP_  ",
        "   _PPPPPPPPPPPPPPPP_   ",
        "    __PPPPPPPPPPPP__    ",
        "      ___PPPPPP___      ",
        "         ______         "
      ],
      "palettes": [ "dump_palette" ],
      "place_signs": [ { "signage": "DUMP", "x": 1, "y": 1 }, { "signage": "DUMP", "x": 22, "y": 1 } ]
    }
  },
  {
    "type": "mapgen",
    "method": "json",
    "om_terrain": "dump",
    "weight": 100,
    "object": {
      "rows": [
        "         ______         ",
        "         ______         ",
        "         ______     7   ",
        "        ________        ",
        "      _____________     ",
        "    ________________  7 ",
        "   __________________   ",
        "   __________________   ",
        "  ____________________  ",
        "  ____________________  ",
        "  _______&&&&&&_______  ",
        "  ____&&&&&&&&&&&&____  ",
        "  __&&&&&&&&&&&&&&&&__  ",
        "  __&&&&&&&^^&&&&&&&__  ",
        "  _&&&&^^^^^^^^^^&&&&_  ",
        "  ^^^^^^^^^^^^^^^^^^^^  ",
        "  ^^^^^^^^^^^^^^^^^^^^  ",
        "  |^^^^^^^^^^^^^^^^^^|  ",
        "  |^^^^^^^^^^^^^^^^^^|  ",
        "  |^^^^^^^^^^^^^^^^^^|  ",
        "  |^^^^^^^^^^^^^^^^^^|  ",
        "  ||||||||||||||||||||  ",
        "                        ",
        "                        "
      ],
      "palettes": [ "dump_palette" ],
      "place_signs": [ { "signage": "<city> Area Dump", "x": 17, "y": 2 } ]
    }
  },
  {
    "type": "mapgen",
    "method": "json",
    "om_terrain": "dump",
    "weight": 100,
    "object": {
      "rows": [
        "         ______         ",
        "         ______         ",
        "         ______         ",
        "      ___________       ",
        "    ________________    ",
        "   __________________   ",
        "   __________________   ",
        "  _____&&&&&&&&&&_____  ",
        "  ___&&&&&&&&&&&&&&___  ",
        "  __&&&&&&&&&&&&&&&&__  ",
        "  _&&&&&&&&&&&&&&&&&&_  ",
        "  _&&&&&&&&&&&&&&&&&&_  ",
        "  _&&&&&&&&&&&&&&&&&&_  ",
        "  _&&&^^^^^^^^^^^^&&&_  ",
        "  _&^^^^^^^^^^^^^^^^&_  ",
        "  _^^^^^^^^^^^^^^^^^^_  ",
        "  _^^^^^^^^^^^^^^^^^^_  ",
        "  _^^^^^^^^^^^^^^^^^^_  ",
        "  _^^^^^^^^^^^^^^^^^^_  ",
        "  _^^^^^^^^^^^^^^^^^^_  ",
        "   _^^^^^^^^^^^^^^^^_   ",
        "    _^^^^^^^^^^^^^^_    ",
        "                        ",
        "                        "
      ],
      "palettes": [ "dump_palette" ],
      "furniture": {
        "^": [ [ "f_rubble", 3 ], "f_null", "f_rubble_rock", "f_wreckage" ],
        "r": [ [ "f_rubble", 3 ], [ "f_null", 6 ], "f_rubble_rock", "f_wreckage" ]
      }
    }
  }
]
