[
  {
    "type": "mapgen",
    "method": "json",
    "om_terrain": [ [ "police_dept_u000", "police_dept_u100" ], [ "police_dept_u010", "police_dept_u110" ] ],
    "object": {
      "fill_ter": "t_linoleum_gray",
      "rows": [
        "sssssssßßssssssssssssssssssssss,,,,,,sssssssssss",
        "ss****sßßs****sssssssssssssssss,,,,,,sssssssssss",
        "###ww##++##ww###ssss##sssssss##,,,,,,##sssssss##",
        "#^_____________#ssss##sssssss##,,,,,,##sssssss##",
        "#_bbbb....bbbb_#sssssssssssssss,,,,,,sssssssssss",
        "#_b││b....b││b_#sssssssssssssss,,,,,,sssssssssss",
        "#_b││b....b││b_#sssssssssssssss,,,,,,sssssssssss",
        "#_bbbb....bbbb_#sssssssssssssss,,,,,,sssssssssss",
        "#_....____...._#sssssssssssssss,,,,,,sssssssssss",
        "#D...._││_...._#######ww#######,,,,,,###########",
        "#F...._││_...._a______________#,,,,,,#:pp:-:pp:#",
        "#_....____..................._#,,,,,,#::::-::::#",
        "#_bbbb.......................B#,,,,,,#::::-::::#",
        "#_b││b.......................B#,,,,,,#::::-::::#",
        "#_b││b.....ccccc.............B#,,,,,,#-=-----=-#",
        "#_bbbb..cccc...cccc.........._#,,,,,,#_._____._#",
        "#_______C_......._C_......____#,,,,,,#_......._#",
        "#||||||||_.......i|_......_|||#,,,,,,#_._qqq___#",
        "#ddd_ddd|_.......i|_......_+_l#,,,,,,#|L|||||||#",
        "#ih___hi|________i|___..___|Sl#,,,,,,#a._|S|__n#",
        "#_______|||||+|||||||_.._|||||#,,,,,,#_._+T|_hn#",
        "#i_______iii____iddd|_.._|a_+T#,,,,,,#_._|||__n#",
        "#d_____d_____dI___h_|_.._|__||#,,,,,,#_._|___hn#",
        "#dh___hd__hI_dh_____+_.._+__+T#,,,,,,#_._+_____#",
        "#d____Id_ddd_d_____d|_.._|S_||#,,,,,,#_._|__h__#",
        "#______________hI_hd|_..h|S_+T#,,,,,,#_._||||||#",
        "#a_____B_____^ddd_id|_..h|||||#,,,,,,#h._C_|___#",
        "#|+www||||+||||||||||_..h|S_+T#,,,,,,#h._C_|_<_#",
        "#n__h__|ii_ii|z:Z|____.._|S_||#,,,,,,#h._C_|_._#",
        "#n_ddd_|_____+::Z|_<...._+__+T#,,,,,,#_._____._#",
        "#n__h_I|ii_ii|::Z|____.._|__||#,,,,,,#_......._#",
        "#|||||||||+||||||||||_.._|a_+T#,,,,,,#________^#",
        "#ao55ee|F_____________.._######,,,,,,##Lww######",
        "#______|D_|||||||||||_.._#sssss,,,,,,sssssssssgs",
        "#__1234||_|______BB_|_.._#s,,,,,,,,,,,,,,,,,,,f ",
        "#_________+_________w_.._ws,,,,,,,,,,,,,,,,,,,f ",
        "#_qnq_qnq_|_nnn_nnn_w_.._Ls,,,,,,,,,,,,,,,,,,,f ",
        "#_qnq_qnq_|_hhh_hhh_w_.._ws,,,,,,,,,,,,,,,,,,,f ",
        "#_qnq_qnq_|_nnn_nnn_|_.._#s,,,,,,,,,,,,,,,,,,,f ",
        "#^________|_hhh_hhh_+_.._#s,,,,,,,,,,,,,,,,,,,f ",
        "####L######||||||||||_..^#s,,,,;,,,,;,,,,;,,,,f ",
        " fsssssss↑#^________+_.._#s,,,,;,,,,;,,,,;,,,,f ",
        " fssssssAA#__nh_nh__|_.._#s,,,,;,,,,;,,,,;,,,,f ",
        " fssssssAA#__nh_nh__w_.._#s,,,,;,,,,;,,,,;,,,,f ",
        " fssssssAA#__nh_nh__w_.._#s,,,,;,,,,;,,,,;,,,,f ",
        " fssssssss#B_nh_nh__w_.._#s,,,,;,,,,;,,,,;,,,,f ",
        " fffgfffff#_________|____#gffffffffffffffffffff ",
        "    s     ################s                     "
      ],
      "palettes": [ "police_dept" ],
      "sealed_item": { "*": { "item": { "item": "seed_rose" }, "furniture": "f_planter_harvest" } },
      "items": {
        "1": [ { "item": "SUS_dishes", "chance": 100 }, { "item": "SUS_silverware", "chance": 100 } ],
        "2": { "item": "SUS_cookware", "chance": 100, "repeat": [ 1, 3 ] },
        "3": [ { "item": "SUS_utensils", "chance": 50 }, { "item": "SUS_knife_drawer", "chance": 50 } ],
        "4": [ { "item": "SUS_breakfast_cupboard", "chance": 30 }, { "item": "SUS_coffee_cupboard", "chance": 50 } ],
        "5": { "item": "SUS_kitchen_sink", "chance": 100 }
      },
      "terrain": { " ": "t_region_groundcover_urban" },
      "furniture": { "1": "f_cupboard", "2": "f_cupboard", "3": "f_cupboard", "4": "f_cupboard", "5": "f_sink" },
      "place_vehicles": [
        { "vehicle": "police_pileup", "x": 44, "y": 43, "chance": 20, "rotation": 90 },
        { "vehicle": "police_pileup", "x": 39, "y": 43, "chance": 20, "rotation": 90 },
        { "vehicle": "police_pileup", "x": 34, "y": 43, "chance": 20, "rotation": 90 },
        { "vehicle": "police_pileup", "x": 29, "y": 43, "chance": 20, "rotation": 90 },
        { "vehicle": "swivel_chair", "x": 42, "y": [ 26, 27 ], "rotation": 90 },
        { "vehicle": "swivel_chair", "x": [ 10, 16 ], "y": [ 16, 18 ], "rotation": 90 },
        { "vehicle": "swivel_chair", "x": [ 10, 16 ], "y": [ 16, 18 ], "rotation": 90 }
      ],
      "place_monsters": [
        { "monster": "GROUP_POLICE", "x": [ 0, 23 ], "y": [ 0, 23 ] },
        { "monster": "GROUP_POLICE", "x": [ 24, 47 ], "y": [ 0, 23 ] },
        { "monster": "GROUP_POLICE", "x": [ 0, 23 ], "y": [ 24, 47 ] },
        { "monster": "GROUP_POLICE", "x": [ 24, 47 ], "y": [ 24, 47 ] }
      ],
      "place_monster": [
        { "monster": "mon_feral_human_pipe", "x": [ 38, 46 ], "y": [ 10, 13 ], "chance": 66, "repeat": [ 1, 3 ] },
        { "monster": "mon_feral_human_crowbar", "x": [ 38, 46 ], "y": [ 10, 13 ], "chance": 25, "repeat": [ 1, 2 ] },
        { "monster": "mon_feral_human_axe", "x": [ 38, 46 ], "y": [ 10, 13 ], "chance": 10 }
      ],
      "place_item": [ { "item": "cig_butt", "x": [ 3, 5 ], "y": [ 41, 42 ], "chance": 80, "repeat": [ 1, 10 ] } ],
      "place_items": [
        { "item": "bulletin_police", "x": 29, "y": 12, "chance": 40, "repeat": [ 1, 3 ] },
        { "item": "bulletin_police", "x": 29, "y": 13, "chance": 40, "repeat": [ 1, 3 ] },
        { "item": "bulletin_police", "x": 29, "y": 14, "chance": 40, "repeat": [ 1, 3 ] }
      ]
    }
  },
  {
    "type": "mapgen",
    "method": "json",
    "om_terrain": [ [ "police_dept_u001", "police_dept_u101" ], [ "police_dept_u011", "police_dept_u111" ] ],
    "object": {
      "fill_ter": "t_linoleum_gray",
      "rows": [
        "                              #_...._#          ",
        "                              #^....^#          ",
        "###ww##ww##ww######ww#ww#######_.__._###########",
        "#**************|ii[ii_ii[ii|_CC_.__._|nnnh__+_S#",
        "#**************|_d[d___d[d_|__C_...._|nnn__h|ll#",
        "w**************|hd[dh_hd[dh|__CC...._L_hh_hh|||#",
        "w**************|_d[d___d[d_|___C...._|____hh___#",
        "#**************|___________|__CC.__._|hhh__h___#",
        "#**************|a____ii___^|__C_.__._|hhhhh____#",
        "w******########||+|wwwww|+||_CC_...._||||||||||#",
        "w******#^__________________a____....______^|T|T#",
        "#******#_qqqq_............................_|_|_#",
        "#******#_q││q_............................_|+|+#",
        "w******#_q││q_..____BBB_________qqqq____.._|___#",
        "w******#_qqqq_.._||||||||||||||||||||||_.._+__a#",
        "#******#______.._|4444444444|222222|::|_.._|___#",
        "#******#__FD__.._|4::::::::::::::::≈::|_..i|SSS#",
        "#||||||||||||_.._|4::::::::::::::::|X:|_..i||||#",
        "#!|!|yyyyyyy|_.._|4::4444::4|222222|::|_..i|SSS#",
        "#___|_______|_.._|4::4##4::4||||||||Y:|_.._|___#",
        "#___+_qqqqq_+_.._|4::4##4::4|}[[[[[|Y:|_.._+__a#",
        "#!|!|_______|_..h|4::4444::4|}:::::|::|_.._|___#",
        "#||||yyyyyyy|_..h|4::::::::4|{:ppp:|x:|_..i|+|+#",
        "#||||yyyyyyy|_..h|4::::::::4|]:::::≈::|_..i|_|_#",
        "#!|!|_______|_..h|4444444444|333335|::|_..i|T|T#",
        "#___+_qqqqq_+_.._||||||||||||||||||||L|_.._||||#",
        "#___|_______|_.._L::/|2:222222222:2|i___.._|___#",
        "#!|!|yyyyyyy|_.._|||||2:::::::::::2|i___.._|_>_#",
        "#||||||||||||^.._|___|2:222222222:2|__|_.._|_._#",
        "#____ééé__a_|_.._|_>_|2:222222222:2|__C_..___._#",
        "#___________+_.._|_._|2:::::::::::2|__C_......_#",
        "#___________|_..___._|2:222222222:2|__C___hhh__#",
        "#__________qw_......_||L|###############ww######",
        "#__________qw_.._____|i_i#                      ",
        "#__________qw_.._|CCC|i_i#                      ",
        "#___________w_.._|_h_ii_i#                      ",
        "#__________qw_.._|______i#                      ",
        "#__________qw_.._|iiiii_i#                      ",
        "#__________qw_.._L_______#                      ",
        "#___________|____|iiiiiii#                      ",
        "####WWWW######ww##########                      ",
        "          0~~~~~~~~~~~~~~0                      ",
        "          6~~~~~~~~~~~~~~6                      ",
        "          6~~~~~~~~~~~~~~6                      ",
        "          6~~~~~~~~~~~~~~6                      ",
        "          6~~~~~~~~~~~~~~6                      ",
        "          6~~~~~~~~~~~~~~6                      ",
        "          6666666666666666                      "
      ],
      "palettes": [ "police_dept" ],
      "place_nested": [ { "chunks": [ "11x11_gym_open" ], "x": 1, "y": 29 } ],
      "items": {
        "2": { "item": "SUS_office_filing_cabinet", "chance": 100, "repeat": [ 1, 3 ] },
        "3": { "item": "cop_items", "chance": 90, "repeat": [ 3, 6 ] },
        "4": { "item": "cop_evidence", "chance": 60, "repeat": [ 2, 4 ] },
        "{": { "item": "police_armory_any_sniperrifle", "chance": 50 },
        "}": { "item": "police_armory_any_assaultrifle", "chance": 100 },
        "[": { "item": "police_armory_any_pistol", "chance": 100 },
        "]": { "item": "police_armory_any_shotgun", "chance": 50 }
      },
      "furniture": {
        "2": "f_rack",
        "3": "f_locker",
        "4": "f_rack",
        "5": "f_locker",
        "{": "f_locker",
        "}": "f_locker",
        "[": "f_locker",
        "]": "f_locker"
      },
      "terrain": {
        " ": "t_open_air",
        "2": "t_thconc_floor",
        "3": "t_thconc_floor",
        "4": "t_thconc_floor",
        "5": "t_thconc_floor",
        "Y": "t_thconc_floor",
        "*": "t_open_air_rooved",
        "6": "t_gutter",
        "0": "t_gutter_drop"
      },
      "place_vehicles": [
        { "vehicle": "swivel_chair", "x": [ 36, 37 ], "y": [ 29, 31 ], "rotation": 90 },
        { "vehicle": "swivel_chair", "x": [ 28, 29 ], "y": [ 5, 7 ], "rotation": 90 },
        { "vehicle": "swivel_chair", "x": 44, "y": [ 6, 8 ], "rotation": 90 },
        { "vehicle": "swivel_chair", "x": 45, "y": [ 6, 8 ], "rotation": 90 },
        { "vehicle": "swivel_chair", "x": 46, "y": [ 6, 8 ], "rotation": 90 }
      ],
      "place_monsters": [
        { "monster": "GROUP_POLICE", "x": [ 0, 23 ], "y": [ 0, 23 ] },
        { "monster": "GROUP_POLICE", "x": [ 24, 47 ], "y": [ 0, 23 ] },
        { "monster": "GROUP_POLICE", "x": [ 0, 23 ], "y": [ 24, 47 ] },
        { "monster": "GROUP_POLICE", "x": [ 24, 47 ], "y": [ 24, 47 ] }
      ]
    }
  },
  {
    "type": "mapgen",
    "method": "json",
    "om_terrain": [ [ "police_dept_u002", "police_dept_u102" ], [ "police_dept_u012", "police_dept_u112" ] ],
    "object": {
      "fill_ter": "t_tar_flat_roof",
      "rows": [
        "                              -......-          ",
        "                              -......-          ",
        "5------------------------------..oo..----------5",
        "-................................oo............-",
        "-..............................................-",
        "-..oo......oo..................................-",
        "-..oo......oo..................................-",
        "-................................oo............-",
        "-................................oo............-",
        "-..............................................-",
        "-..............................................-",
        "-..............................................-",
        "-..............................................-",
        "-..oo..........................................-",
        "-..oo..........................................-",
        "-..............................................-",
        "-..............................................-",
        "-..............................................-",
        "-..............................................-",
        "-..............................................-",
        "-..............................................-",
        "-..............................................-",
        "-..............................................-",
        "-..............................................-",
        "-..............................................-",
        "-..............................................-",
        "-...................>..........................-",
        "-..............................................-",
        "-..............................................-",
        "-..............................................-",
        "-..............................................-",
        "-..............................................-",
        "-........................----------------------5",
        "-........................-                      ",
        "-........................-                      ",
        "-........................-                      ",
        "-........................-                      ",
        "-........................-                      ",
        "-........................-                      ",
        "-........................-                      ",
        "5------------------------5                      ",
        "                                                ",
        "                                                ",
        "                                                ",
        "                                                ",
        "                                                ",
        "                                                ",
        "                                                "
      ],
      "palettes": [ "roof_palette" ],
      "terrain": { ">": "t_ladder_down" },
      "place_nested": [
        { "chunks": [ [ "roof_4x4_utility", 1 ], [ "roof_4x4_utility_1", 1 ], [ "roof_6x6_utility", 1 ] ], "x": 3, "y": 32 },
        {
          "chunks": [ [ "roof_2x2_infrastructure", 1 ], [ "roof_2x2_infrastructure_1", 2 ], [ "roof_2x2_infrastructure_2", 1 ] ],
          "x": 44,
          "y": 4
        },
        {
          "chunks": [ [ "roof_2x2_infrastructure", 1 ], [ "roof_2x2_infrastructure_1", 2 ], [ "roof_2x2_infrastructure_2", 1 ] ],
          "x": 44,
          "y": 29
        }
      ]
    }
  },
  {
    "type": "mapgen",
    "method": "json",
    "om_terrain": [ [ "police_dept_b10", "police_dept_b00" ], [ "police_dept_b11", "police_dept_b01" ] ],
    "object": {
      "fill_ter": "t_thconc_floor",
      "rows": [
        "                                                ",
        "                                                ",
        "                           #####################",
        "                           #:::::::::::::::::::#",
        "                           #:;;;;;;;:#:;;;;;;;:#",
        "                           #:;,,,,,;:::;,,,,,;:#",
        "                           #:;,,,,,;:::;,,,,,;:#",
        "          ########         #:;,,,,,;:::;,,,,,;:#",
        "          #::::::#         #:;,,,,,;:::;,,,,,;:#",
        "          #::::::#         #:;,,,,,;:::;,,,,,;:#",
        "###########::<<::###########:;,,,,,;:::;,,,,,;:#",
        "#:1111111:#::<<::#:1111111:#:;,,,,,;:::;,,,,,;:#",
        "#:2222222:#::::::#:2222222:#:;,,,,,;:::;,,,,,;:#",
        "#:,,,,,,,:#::::::#:,,,,,,,:#:;;;;;;;:#:;;;;;;;:#",
        "#:,,,,,,,::::::::::,,,,,,,:::,,,,,,,:::,,,,,,,:#",
        "#:,,,,,,,,,,,,,,,,,,,,,,,,,,,,,,,,,,,,,,,,,,,,:#",
        "#:,,,,,,,,,,,,,,,,,,,,,,,,,,,,,,,,,,,,,,,,,,,,:#",
        "#:,,,,,,,,,,,,,,,,,,,,,,,,,,,,,,,,,,,,,,,,,,,,:#",
        "#:,,,,,,,,,,,,,,,,,,,,,,,,,,,,,,,,,,,,,,,,,,,,:#",
        "#:,,,,,,,,,,,,,,,,,,,,,,,,,,,,,,,,,,,,,,,,,,,,:#",
        "#:,,,,,,,,,,,,,,,,,,,,,,,,,,,,,,,,,,,,,,,,,,,,:#",
        "#:,,,,,,,,,,,,,,,,,,,,,,,,,,,,,,,,,,,,,,,,,,,,:#",
        "#:,,,,,,,,,,,,,,,,,,,,,,,,,,,,,,,,,,,,,,,,,,,,:#",
        "#:,,,,,,,:::,,,,,,,,,,,,,,,,,,,,,,,,:::,,,,,,,:#",
        "#:,,,,,,,:#:,,,,,,,,,,,,,,,,,,,,,,,,:#:,,,,,,,:#",
        "#:,,,,,,,:::,,,,,,,,,,,,,,,,,,,,,,,,:::,,,,,,,:#",
        "#:,,,,,,,,,,,,,,,,,,,,,,,,,,,,,,,,,,,,,,,,,,,,:#",
        "#:,,,,,,,,,,,,,,,,,,,,,,,,,,,,,,,,,,,,,,,,,,,,:#",
        "#:,,,,,,,,,,,,,,,,,,,,,,,,,,,,,,,,,,,,,,,,,,,,:#",
        "#:,,,,,,,,,,,,,,,,,,,,,,,,,,,,,,,,,,,,,,,,,,,,:#",
        "#:,,,,,,,,,,,,,,,,,,,,,,,,,,,,,,,,,,,,,,,,,,,,:#",
        "#:,,,,,,,,,,,,,,,,,,,,,,,,,,,,,,,,,,,,,,,,,,,,:#",
        "#:,,,,,,,,,,,,,,,,,,,,,,,,,,,,,,,,,,,,,,,,,,,,:#",
        "#:,,,,,,,,,,,,,,,,,,,,,,,,,,,,,,,,,,,,,,,,,,,,:#",
        "#:,,,,,,,:::,,,,,,,::::::::::,,,,,,,:::,,,,,,,:#",
        "#:;;;;;;;:#:;;;;;;;:########:;;;;;;;:#:;;;;;;;:#",
        "#:;,,,,,;:::;,,,,,;:#444444#:;,,,,,;:::;,,,,,;:#",
        "#:;,,,,,;:::;,,,,,;:#444444#:;,,,,,;:::;,,,,,;:#",
        "#:;,,,,,;:::;,,,,,;:#444444#:;,,,,,;:::;,,,,,;:#",
        "#:;,,,,,;:::;,,,,,;:L::::::L:;,,,,,;:::;,,,,,;:#",
        "#:;,,,,,;:::;,,,,,;:#4444:3#:;,,,,,;:::;,,,,,;:#",
        "#:;,,,,,;:::;,,,,,;:#4444:3#:;,,,,,;:::;,,,,,;:#",
        "#:;,,,,,;:::;,,,,,;:#4444:3#:;,,,,,;:::;,,,,,;:#",
        "#:;,,,,,;:::;,,,,,;:###fg###:;,,,,,;:::;,,,,,;:#",
        "#:;;;;;;;:#:;;;;;;;:# #55# #:;;;;;;;:#:;;;;;;;:#",
        "#:::::::::::::::::::# #### #:::::::::::::::::::#",
        "#####################      #####################",
        "                                                "
      ],
      "palettes": [ "police_dept" ],
      "terrain": { "1": "t_ramp_up_high", "2": "t_ramp_up_low", " ": "t_soil" },
      "furniture": {
        "4": [ [ "f_barricade_road", 5 ], [ "f_null", 2 ] ],
        "5": [
          [ "f_generator_broken", 25 ],
          [ "f_diesel_generator", 5 ],
          [ "f_military_generator", 5 ],
          [ "f_12000_gasoline_generator", 5 ]
        ],
        "3": "f_utility_shelf"
      },
      "items": { "3": [ { "item": "mechanics", "chance": 80 } ] },
      "place_vehicles": [
        { "vehicle": "truck_swat", "x": 33, "y": 10, "chance": 33, "rotation": 90 },
        { "vehicle": "truck_swat", "x": 43, "y": 10, "chance": 33, "rotation": 90 },
        { "vehicle": "truck_swat", "x": 4, "y": 37, "chance": 33, "rotation": 270 },
        { "vehicle": "truck_swat", "x": 14, "y": 37, "chance": 33, "rotation": 270 },
        { "vehicle": "truck_swat", "x": 41, "y": 37, "chance": 33, "rotation": 270 },
        { "vehicle": "truck_swat", "x": 31, "y": 37, "chance": 33, "rotation": 270 }
      ],
      "place_monsters": [
        { "monster": "GROUP_POLICE", "x": [ 0, 23 ], "y": [ 0, 23 ] },
        { "monster": "GROUP_POLICE", "x": [ 24, 47 ], "y": [ 0, 23 ] },
        { "monster": "GROUP_POLICE", "x": [ 0, 23 ], "y": [ 24, 47 ] },
        { "monster": "GROUP_POLICE", "x": [ 24, 47 ], "y": [ 24, 47 ] }
      ]
    }
  },
  {
    "type": "mapgen",
    "method": "json",
    "om_terrain": [ [ "police_dept_d100", "police_dept_d000" ], [ "police_dept_d110", "police_dept_d010" ] ],
    "object": {
      "fill_ter": "t_linoleum_gray",
      "rows": [
        "ss,,,,,,,ssssssssss,,,,,,,ssßßßßßßßßßßßßßßßßßßßß",
        "ss,,,,,,,ssssssssss,,,,,,,ssßssssssssssssssssssß",
        "##,,,,,,,##ssssss##,,,,,,,##ßs*******ss*******sß",
        "##≈≈≈≈≈≈≈##ssssss##≈≈≈≈≈≈≈##ßs*     *ss*     *sß",
        "#:,,,,,,,&#ssssss#&,,,,,,,:#ßs*     *ss*     *sß",
        "#:,,,;,,,:#ssssss#:,,,;,,,:#ßs*  3  *ss*  3  *sß",
        "#:,,;;;,,:#ssssss#:,,,;,,,:#ßs*     *ss*     *sß",
        "#:,;,;,;,:########:,;,;,;,:#ßs*     *ss*     *sß",
        "#:,,,;,,,:|::::::|:,,;;;,,:#ßs*******ss*******sß",
        "#:,,,;,,,:L::::::L:,,,;,,,:#ßssssssssssssssssssß",
        "#:,,,,,,,:|::>>::|:,,,,,,,:#ßßßßßßßßßßßßßßßßßßßß",
        "#:1111111:|::>>::|:1111111:#####www##++##www####",
        "#:2222222:|::::::|:2222222:|^_________________^#",
        "#:::::::::|::::::|:::::::::|_................._#",
        "#||||||||||||LL|||||||||||||_...bbb......bbb.._#",
        "#________________|___hhh_____...b│b......b│b.._#",
        "#_...............L..............bbb......bbb.._#",
        "#_...............L............................B#",
        "#_.______iii_____|___hhh___a_.......cccc......B#",
        "#_._|||L|||||LL||||L|||||+||_.ccccccc..cc.....B#",
        "#_<_|N:::NV::::::|::V:p|___|_.c.........c....._#",
        "#___|N000NV::::::|pNV::|S_T|____iii_____C___.._#",
        "#||||||||||||||==|||||L|||||||||||||||||||||LL|#",
        "#@@:-:::::-:@@|::|:::::pVp:|_DF_a_________|_.._#",
        "#:::=::p::=:::|::-::|::|||:|_______qq_qq__|_..h#",
        "#j:N-:pNp:-N:j|::=::|:::=::L_______nn_nn__|_..h#",
        "#t:p-::p::-p:t|::-::|::|||:|_______qq_qq__|_..h#",
        "#||||:::::|||||::|:::::pVp:|______________L_.._#",
        "#@@:-:::::-:@@|::|||||||||||wwww|__qq_qq__|_..h#",
        "#:::=:::::=:::|::-:::|!!!!!|d999w__nn_nn__|_..h#",
        "#j:N-:::::-N:j|::=:<:|:::::|d_h_+__qq_qq__|_..h#",
        "#t:p-::p::-p:t|::-:::|!!:!!|d___w_________|____#",
        "#||||:pNp:|||||::|||||||+|||||||||||||||||##LL##",
        "#@@:-::p::-:@@|::=:::::::::L'''''HHHH''***#'''f ",
        "#:::=:::::=:::|::=:::::::::L'''''''''''***#'''f ",
        "#j:N-:::::-N:j|::|||||||||||''''''''''''**#'''f ",
        "#t:p-:::::-p:t|::|777|oo8ee|''''''''''''''#'''f ",
        "#||||:::::|||||::|:::L:::::v'''''é''é'''''#'''f ",
        "#@@:-::p::-:@@|::|777|:4456|''''''''''''''#'''f ",
        "#:::=:pNp:=:::|::|||||:|CCC|**''''''''''**#'''f ",
        "#j:N-::p::-N:j|::|:::::::::v***''é''é''***#'''f ",
        "#t:p-:::::-p:t|::|:pNp:pNp:|***''''''''***#'''f ",
        "#||||:::::|||||::|:pNp:pNp:################'''f ",
        "#:::::::::::::-::-:pNp:pNp:#''''''''''''''''''f ",
        "#:<<::::::::::=::=:pNp:pNp:#''''''''''''''''''f ",
        "#:<<::::::::::=::=:pNp:pNp:#''''''''''''''''''f ",
        "#::::ppápp::::-::-::::::::á#fffffffffffffffffff ",
        "############################                    "
      ],
      "palettes": [ "police_dept" ],
      "items": {
        "4": [ { "item": "SUS_dishes", "chance": 100 }, { "item": "SUS_silverware", "chance": 100 } ],
        "5": { "item": "SUS_cookware", "chance": 100, "repeat": [ 1, 3 ] },
        "6": [ { "item": "SUS_utensils", "chance": 50 }, { "item": "SUS_knife_drawer", "chance": 33 } ],
        "7": { "item": "SUS_pantry", "chance": 50 },
        "8": { "item": "SUS_kitchen_sink", "chance": 100 }
      },
      "furniture": {
        "3": "f_flagpole",
        "4": "f_cupboard",
        "5": "f_cupboard",
        "6": "f_cupboard",
        "7": "f_rack",
        "8": "f_sink",
        "9": "f_console_broken",
        "0": "f_console_broken"
      },
      "terrain": {
        "1": "t_ramp_down_high",
        "2": "t_ramp_down_low",
        "3": "t_region_groundcover_urban",
        " ": "t_region_groundcover_urban",
        "é": "t_region_groundcover_barren",
        "*": "t_region_shrub_decorative",
        "'": "t_region_groundcover_barren",
        "4": "t_thconc_floor",
        "5": "t_thconc_floor",
        "6": "t_thconc_floor",
        "7": "t_thconc_floor",
        "0": "t_thconc_floor",
        "8": "t_thconc_floor",
        "e": "t_thconc_floor",
        "o": "t_thconc_floor",
        "!": "t_thconc_floor"
      },
      "place_vehicles": [ { "vehicle": "swivel_chair", "x": [ 36, 39 ], "y": [ 20, 21 ], "rotation": 90 } ],
      "place_monsters": [
        { "monster": "GROUP_POLICE", "x": [ 0, 23 ], "y": [ 0, 23 ] },
        { "monster": "GROUP_POLICE", "x": [ 24, 47 ], "y": [ 0, 23 ] },
        { "monster": "GROUP_ZOMBIE_PRISON", "x": [ 0, 23 ], "y": [ 24, 47 ], "density": 0.5 },
        { "monster": "GROUP_ZOMBIE_PRISON", "x": [ 24, 41 ], "y": [ 33, 40 ], "density": 0.5 }
      ],
      "place_item": [
        { "item": "american_flag", "x": 42, "y": 5 },
        { "item": "american_flag", "x": 33, "y": 5 },
        { "item": "g_shovel", "x": 40, "y": 37 },
        { "item": "mess_tray", "x": 26, "y": 39, "repeat": [ 1, 20 ] },
        { "item": "plastic_spoon", "x": 25, "y": 39, "repeat": [ 1, 20 ] },
        { "item": "plastic_knife", "x": 25, "y": 39, "repeat": [ 1, 20 ] },
        { "item": "plastic_fork", "x": 25, "y": 39, "repeat": [ 1, 20 ] },
        { "item": "tin_cup", "x": 24, "y": 39, "repeat": [ 1, 20 ] },
        { "item": "napkin", "x": 24, "y": 39, "repeat": [ 1, 20 ] }
      ]
    }
  },
  {
    "type": "mapgen",
    "method": "json",
    "om_terrain": [ [ "police_dept_d101", "police_dept_d001" ], [ "police_dept_d111", "police_dept_d011" ] ],
    "object": {
      "fill_ter": "t_linoleum_gray",
      "rows": [
        "          #_...._#                              ",
        "          #^....^#                              ",
        "####www####_.__._####www####                    ",
        "#ddd[^_iii|_.__._|YYY___Ema#                    ",
        "#_h_[_____+_...._+________$#                    ",
        "#i_______a|_...._|________£#                    ",
        "#[[[[_[[[[w_...._w_________#                    ",
        "#ddd[_[dddw_.__._w__C___C__#                    ",
        "#_h_[_[__hw_.__._w__C___C__#                    ",
        "#i_______iw_...._w__C___C__#                    ",
        "#[[[[_[[[[w_...._w__S___S__#                    ",
        "#ddd[_[dddw_...._w__M___M__#####www########www##",
        "#h__[_[_h_w_.__._w__M___M__|/|^_qqq_^|n__hhh__e#",
        "#i_______i|_.__._|_________|:|_______|________e#",
        "#|||www||||_...._||||www||||L|__qqq__|+|a_____o#",
        "#___________...._____iii_______________w?_____C#",
        "#_...................................._w?_n___C#",
        "#_...................................._w?_____C#",
        "#_._________qqqq____________________.._w????__C#",
        "#_._||||||||||||||||||||L||||||||||_.._||||||||#",
        "#_>_|j@|@j|t:á|::=:::L::::y|_h_dhh|_.._|a_____^#",
        "#___|t:|:t|j::+::=:::L::p:y|_ddd__+_.._+_______#",
        "#|||||≈|≈||||||::|||||0:p:y|_____^|_.._|__hhh__#",
        "#@@:-:::::-:@@|::|2:3|0:p:y|||||+||_.._|_hnnnh_#",
        "#:::=:---:=:::|::|2:3|0:p:y|a____h|_.._|_hnnnh_#",
        "#j:N-:-*-:-N:j|::L::p|0:::y|i_dd__+_.._|_hnnnh_#",
        "#t:p-:-*-:-p:t|::|2:3|||||||i_hd_?|_.._|_hnnnh_#",
        "#||||:-*-:|||||::|2:3|5:::8|i__d_?|_.._|_hnnnh_#",
        "#@@:-:-*-:-:@@|::|||||6:9:8||||||||_.._|_hnnnh_#",
        "#:::=:-*-:=:::|::-:::-::9:8|i____^|_.._|__hhh__#",
        "#j:N-:-*-:-N:j|::=:>:=::9:8|i__d__+_.._+_______#",
        "#t:p-:-*-:-p:t|::-:::-á:::8|a_hd__|____|__iii_^#",
        "#||||:-*-:|||||::||||||||||#####################",
        "#@@:-:-*-:-:@@|::|PPPPPPPPP#              1     ",
        "#:::=:-*-:=:::|::|:::::::::v              1     ",
        "#j:N-:-*-:-N:j|::|:NN:::NN:#              1     ",
        "#t:p-:-*-:-p:t|::|:pp:::pp:#              1     ",
        "#||||:-*-:|||||::L:::::::::v              1     ",
        "#@@:-:-*-:-:@@|::|:pp:::pp:#              1     ",
        "#:::=:-*-:=:::|::|:NN:::NN:#              1     ",
        "#j:N-:-*-:-N:j|::|:::::::::v              1     ",
        "#t:p-:-*-:-p:t|::|PPPPPPPPP#              1     ",
        "#||||:-*-:|||||::||||||||||#111111111111111     ",
        "#:::::-*-:-:@@|::-::ppp:::4#                    ",
        "#:>>::-*-:=:::|::=::::::::4#                    ",
        "#:>>::---:-N:j|::-:@:@:@::4#                    ",
        "#:::::::::-p:t|::-:@:@:@::4#                    ",
        "#######v####################                    "
      ],
      "palettes": [ "police_dept" ],
      "furniture": {
        "0": "f_console_broken",
        "2": "f_washer",
        "3": "f_dryer",
        "4": "f_locker",
        "5": "f_heavy_lathe",
        "6": "f_drill_press",
        "8": "f_counter",
        "9": "f_workbench"
      },
      "terrain": {
        " ": "t_open_air",
        "*": "t_open_air_rooved",
        "1": "t_fence_barbed",
        "7": "t_window_bars",
        "y": "t_thconc_floor",
        "P": "t_thconc_floor",
        "0": "t_thconc_floor",
        "2": "t_thconc_floor",
        "3": "t_thconc_floor",
        "4": "t_thconc_floor",
        "5": "t_thconc_floor",
        "6": "t_thconc_floor",
        "8": "t_thconc_floor",
        "9": "t_thconc_floor"
      },
      "items": {
        "2": [ { "item": "prison_textile", "chance": 100, "repeat": [ 1, 5 ] } ],
        "3": [ { "item": "prison_textile", "chance": 100, "repeat": [ 1, 5 ] } ],
        "4": [ { "item": "softdrugs", "chance": 40, "repeat": [ 1, 3 ] }, { "item": "harddrugs", "chance": 40, "repeat": [ 1, 3 ] } ],
        "8": { "item": "hand_tools", "chance": 40 }
      },
      "place_item": [
        { "item": "coffeemaker", "x": 38, "y": 12 },
        { "item": "television", "x": 47, "y": 16 },
        { "item": "microwave", "x": 47, "y": 14 },
        { "item": "microscope", "x": 20, "y": [ 7, 12 ], "chance": 80 },
        { "item": "microscope", "x": 24, "y": [ 7, 12 ], "chance": 80 },
        { "item": "test_tube", "x": 20, "y": [ 7, 12 ], "repeat": [ 1, 3 ], "chance": 33 },
        { "item": "test_tube", "x": 24, "y": [ 7, 12 ], "repeat": [ 1, 3 ], "chance": 33 },
        { "item": "rack_test_tube", "x": 20, "y": [ 7, 12 ], "chance": 20 },
        { "item": "rack_test_tube", "x": 24, "y": [ 7, 12 ], "chance": 20 },
        { "item": "funnel_separation", "x": 20, "y": [ 7, 12 ], "chance": 10 },
        { "item": "funnel_separation", "x": 24, "y": [ 7, 12 ], "chance": 10 },
        { "item": "analytical_set_basic", "x": 20, "y": [ 7, 12 ], "chance": 6 },
        { "item": "analytical_set_basic", "x": 24, "y": [ 7, 12 ], "chance": 6 }
      ],
      "place_vehicles": [
        { "vehicle": "swivel_chair", "x": 19, "y": [ 7, 12 ], "rotation": 90 },
        { "vehicle": "swivel_chair", "x": 25, "y": [ 7, 12 ], "rotation": 90 }
      ],
      "place_monsters": [
        { "monster": "GROUP_POLICE", "x": [ 0, 23 ], "y": [ 0, 23 ] },
        { "monster": "GROUP_POLICE", "x": [ 24, 47 ], "y": [ 0, 23 ] },
        { "monster": "GROUP_POLICE", "x": [ 24, 47 ], "y": [ 24, 32 ] },
        { "monster": "GROUP_ZOMBIE_PRISON", "x": [ 0, 23 ], "y": [ 24, 47 ], "density": 0.5 }
      ]
    }
  },
  {
    "type": "mapgen",
    "method": "json",
    "om_terrain": [ [ "police_dept_d102", "police_dept_d002" ], [ "police_dept_d112", "police_dept_d012" ] ],
    "object": {
      "fill_ter": "t_tar_flat_roof",
      "rows": [
        "          -......-                              ",
        "          -......-                              ",
        "5----------..oo..----------5                    ",
        "-............oo............-                    ",
        "-..........................-                    ",
        "-..........................-                    ",
        "-..........................-                    ",
        "-............oo............-                    ",
        "-............oo............-                    ",
        "-..........................-                    ",
        "-..........................-                    ",
        "-..........................5-------------------5",
        "-............oo.............v..................-",
        "-............oo................................-",
        "-..............................................-",
        "-..............................................-",
        "-..............................................-",
        "-..............................................-",
        "-..............................................-",
        "-..............................................-",
        "-..............................................-",
        "-..............................................-",
        "-..............................................-",
        "-..............................................-",
        "-.....ooo......................................-",
        "-.....ooo......................................-",
        "-.....ooo......................................-",
        "-..............................................-",
        "-..............................................-",
        "-..............................................-",
        "-..............................................-",
        "-.....ooo......................................-",
        "-.....ooo..................--------------------5",
        "-.....ooo..................-                    ",
        "-..........................-                    ",
        "-..........................-                    ",
        "-..........................-                    ",
        "-..........................-                    ",
        "-.....ooo..................-                    ",
        "-.....ooo..................-                    ",
        "-.....ooo..................-                    ",
        "-..........................-                    ",
        "-..........................-                    ",
        "-..........................-                    ",
        "-..........................-                    ",
        "-..........................-                    ",
        "-..........................-                    ",
        "5--------------------------5                    "
      ],
      "palettes": [ "roof_palette" ],
      "place_nested": [
        { "chunks": [ [ "roof_4x4_utility", 1 ], [ "roof_4x4_utility_1", 1 ], [ "roof_6x6_utility", 1 ] ], "x": 2, "y": 4 },
        {
          "chunks": [ [ "roof_4x4_survivor", 2 ], [ "roof_6x6_survivor", 1 ], [ "null", 9 ] ],
          "x": [ 10, 18 ],
          "y": [ 32, 40 ]
        },
        {
          "chunks": [ [ "roof_2x2_infrastructure", 1 ], [ "roof_2x2_infrastructure_1", 2 ], [ "roof_2x2_infrastructure_2", 1 ] ],
          "x": 44,
          "y": 29
        }
      ]
    }
  },
  {
    "type": "mapgen",
    "method": "json",
    "om_terrain": [ "police_dept_skyway" ],
    "object": {
      "fill_ter": "t_linoleum_white",
      "rows": [
        "      W_...._W          ",
        "      W_.__._W          ",
        "      W_.__._W          ",
        "      W_...._W          ",
        "      W_...._W          ",
        "      W_...._W          ",
        "      W_.__._W          ",
        "      #_.__._#          ",
        "      #_...._#          ",
        "      W_...._W          ",
        "      W_...._W          ",
        "      W_.__._W          ",
        "      W_.__._W          ",
        "      W_...._W          ",
        "      W_...._W          ",
        "      #_...._#          ",
        "      #_.__._#          ",
        "      W_.__._W          ",
        "      W_...._W          ",
        "      W_...._W          ",
        "      W_...._W          ",
        "      W_.__._W          ",
        "      W_.__._W          ",
        "      W_...._W          "
      ],
      "palettes": [ "police_dept" ],
      "terrain": { " ": "t_open_air" },
      "place_monsters": [ { "monster": "GROUP_POLICE", "x": [ 7, 12 ], "y": [ 0, 23 ] } ]
    }
  },
  {
    "type": "mapgen",
    "method": "json",
    "om_terrain": [ "police_dept_skyway_roof" ],
    "object": {
      "fill_ter": "t_tar_flat_roof",
      "rows": [
        "      -......-          ",
        "      -..oo..-          ",
        "      -..oo..-          ",
        "      -......-          ",
        "      -......-          ",
        "      -......-          ",
        "      -..oo..-          ",
        "      -..oo..-          ",
        "      -......-          ",
        "      -......-          ",
        "      -......-          ",
        "      -..oo..-          ",
        "      -..oo..-          ",
        "      -......-          ",
        "      -......-          ",
        "      -......-          ",
        "      -..oo..-          ",
        "      -..oo..-          ",
        "      -......-          ",
        "      -......-          ",
        "      -......-          ",
        "      -..oo..-          ",
        "      -..oo..-          ",
        "      -......-          "
      ],
      "palettes": [ "roof_palette" ]
    }
  }
]
