[
  {
    "id": "mon_feral_scientist_psychic",
    "type": "MONSTER",
    "name": { "str": "Dr. Brain" },
    "description": "An ordinary-looking scientist lost amid the carnage, were it not for the bloodshot eyes, the enlarged cranium, and the fact that the zombies ignore them.  Bits of paper and chemistry equipment lazily float in the air near them.",
    "//": "This is supposed to be a rare boss kind of monster, with both telepathic and telekinetic abililites, but no tougher than a normal zombie.",
    "default_faction": "science",
    "looks_like": "chud",
    "bodytype": "human",
    "species": [ "HUMAN" ],
    "volume": "62500 ml",
    "weight": "81500 g",
    "hp": 85,
    "speed": 100,
    "material": [ "flesh" ],
    "symbol": "@",
    "color": "magenta",
    "aggression": 30,
    "morale": 100,
    "melee_skill": 4,
    "melee_dice": 1,
    "melee_dice_sides": 3,
    "melee_damage": [ { "damage_type": "cut", "amount": 2 } ],
    "armor": { "bash": 15, "cut": 10, "bullet": 35, "stab": 5 },
    "weakpoint_sets": [ "wps_humanoid_body" ],
    "families": [ "prof_intro_biology", "prof_physiology" ],
    "dodge": 2,
    "harvest": "human",
    "dissect": "dissect_human_sample_single",
    "path_settings": { "max_dist": 30, "avoid_traps": true, "avoid_sharp": true },
    "vision_day": 50,
    "vision_night": 3,
    "death_drops": "feral_scientists_death_drops_psychic",
    "zombify_into": "mon_zombie_scientist",
    "anger_triggers": [ "FRIEND_DIED", "FRIEND_ATTACKED", "HURT", "PLAYER_CLOSE" ],
    "special_attacks": [
      [ "PARROT_AT_DANGER", 15 ],
      {
        "id": "psi_drbrain_flashbang",
        "type": "spell",
        "spell_data": { "id": "telepathic_confusion_monster", "min_level": 5 },
        "cooldown": 12,
        "monster_message": "A roar fills %3$s's mind and the world is blotted out!"
      },
      {
        "id": "psi_drbrain_blast",
        "type": "spell",
        "spell_data": { "id": "telepathic_blast_monster", "min_level": 4 },
        "cooldown": 10,
        "monster_message": "%1$s stares at %3$s!"
      },
      {
        "id": "psi_drbrain_mindhammer",
        "type": "spell",
        "spell_data": { "id": "telekinetic_hammer_monster", "min_level": 6 },
        "cooldown": 12,
        "monster_message": "%1$s hammers %3$s with psionic force!"
      },
      {
        "id": "smash",
        "move_cost": 80,
        "cooldown": 8,
        "damage_max_instance": [ { "damage_type": "psi_telekinetic_damage", "amount": 20, "armor_penetration": 10 } ],
        "hitsize_min": 12,
        "range": 8,
        "throw_strength": 100,
        "blockable": false,
        "effects_require_dmg": false,
        "hit_dmg_u": "%1$s stares at you and a powerful force hurls you through the air!",
        "hit_dmg_npc": "%1$s stares at <npcname> and a powerful force hurls them through the air!",
        "miss_msg_u": "%s stares at you, and you feel a crushing pressure for a moment before the feeling vanishes!",
        "miss_msg_npc": "%s stares at <npcname> but nothing happens!"
      },
      [ "PULL_METAL_WEAPON", 8 ],
      [ "FEAR_PARALYZE", 10 ]
    ],
    "flags": [
      "SEES",
      "HEARS",
      "SMELLS",
      "WARM",
      "BASHES",
      "GROUP_BASH",
      "HUMAN",
      "CAN_OPEN_DOORS",
      "PATH_AVOID_DANGER_2",
      "PATH_AVOID_FIRE",
      "TEEP_IMMUNE"
    ]
  },
  {
    "id": "mon_feral_security_psychic",
    "type": "MONSTER",
    "name": "feral security guard, Ψ Division",
    "description": "A security guard gone feral, or so you thought.  As you look closer, you notice the relatively-normal appearance, the clear eyes, and the patch on their uniform with a Ψ shape in front of the logo of XEDRA.  The zombies around them ignore them as they move smoothly and purposefully through the ruins.",
    "default_faction": "science",
    "looks_like": "chud",
    "bodytype": "human",
    "species": [ "HUMAN" ],
    "volume": "62500 ml",
    "weight": "81500 g",
    "hp": 120,
    "speed": 110,
    "material": [ "flesh" ],
    "color": "pink",
    "symbol": "@",
    "aggression": 30,
    "morale": 100,
    "melee_skill": 6,
    "melee_dice": 2,
    "melee_dice_sides": 5,
    "melee_damage": [ { "damage_type": "bash", "amount": 6 } ],
    "attack_cost": 85,
    "weakpoint_sets": [ "wps_humanoid_body" ],
    "families": [ "prof_intro_biology", "prof_physiology" ],
    "dodge": 5,
    "armor": { "bash": 8, "cut": 6, "stab": 6, "bullet": 10 },
    "harvest": "human",
    "dissect": "dissect_human_sample_single",
    "vision_day": 35,
    "vision_night": 7,
    "path_settings": { "max_dist": 30, "allow_open_doors": true, "avoid_traps": true, "avoid_sharp": true },
    "death_drops": "feral_security_death_drops_psychic",
    "zombify_into": "mon_zombie_survivor",
    "anger_triggers": [ "FRIEND_DIED", "FRIEND_ATTACKED", "HURT" ],
    "special_attacks": [
      [ "PARROT_AT_DANGER", 15 ],
      { "id": "smash", "attack_upper": true, "throw_strength": 50, "cooldown": 15 },
      [ "BIO_OP_DISARM", 15 ],
      { "id": "bio_op_takedown", "cooldown": 20 }
    ],
    "flags": [
      "SEES",
      "HEARS",
      "SMELLS",
      "WARM",
      "BASHES",
      "GROUP_BASH",
      "HUMAN",
      "CAN_OPEN_DOORS",
      "PATH_AVOID_DANGER_1",
      "PATH_AVOID_FIRE",
      "PRIORITIZE_TARGETS",
      "STUN_IMMUNE"
    ]
  },
  {
    "id": "mon_feral_security_captain_psychic",
    "type": "MONSTER",
    "copy-from": "mon_feral_human_bio3",
    "name": "feral security captain, Ψ Division",
    "looks_like": "chud",
    "description": "A feral security guard with a military-style uniform, bearing the XEDRA logo and some kind of rank insignia.  Their movements are precise, controlled, and inhumanly smooth, and while their eyes are still bloodshot, they have a spark lacking in most ferals you've seen.",
    "death_drops": "feral_security_captain_death_drops_psychic"
  }
]
