[
  {
    "id": "manatouched_serum",
    "copy-from": "iv_mutagen_flavor",
    "type": "ITEM",
    "subtypes": [ "COMESTIBLE" ],
    "name": { "str_sp": "concentrated mana mutagenic primer" },
    "color": "light_blue",
    "description": "A very concentrated form of mana potion.",
    "use_action": {
      "type": "consume_drug",
      "activation_message": "You inject the %s.",
      "tools_needed": { "syringe": -1 },
      "vitamins": [ [ "mutagen_manatouched", 500 ] ]
    }
  },
  {
    "id": "manatouched_mutagen",
    "copy-from": "mutagen_flavor",
    "type": "ITEM",
    "subtypes": [ "COMESTIBLE" ],
    "color": "light_blue",
    "description": "A mana potion mixed with mutagen.  It might help you connect with magic.",
    "name": { "str_sp": "mana mutagen" },
    "use_action": {
      "type": "consume_drug",
      "activation_message": "You drink the %s.",
      "vitamins": [ [ "mutagen_manatouched", 175 ], [ "mutagen", 125 ] ]
    }
  },
  {
    "id": "mutagen_black_dragon",
    "copy-from": "mutagen_flavor",
    "type": "ITEM",
    "subtypes": [ "COMESTIBLE" ],
    "color": "black",
    "description": "An alchemic concoction made from the remains of a slain black dragon and a bit of potion base.  Ancient and Academic texts talk of profound changes from consuming this.",
    "name": { "str_sp": "black dragon mutagen" },
    "use_action": {
      "type": "consume_drug",
      "activation_message": "You drink the %s.",
      "vitamins": [ [ "mutagen_black_dragon", 175 ], [ "mutagen", 125 ] ]
    }
  },
  {
    "id": "iv_black_dragon",
    "copy-from": "iv_mutagen_flavor",
    "type": "ITEM",
    "subtypes": [ "COMESTIBLE" ],
    "name": { "str_sp": "black dragon mutagenic primer" },
    "description": "A super-concentrated mutagen that seems to swirl with the anger of a black dragon.  Do you dare leave your humanity behind and inject it?",
    "color": "black",
    "use_action": {
      "type": "consume_drug",
      "activation_message": "You inject the %s.",
      "tools_needed": { "syringe": -1 },
      "vitamins": [ [ "mutagen_black_dragon", 500 ] ]
    }
  }
]
