[
  {
    "type": "mapgen",
    "om_terrain": [ "mil_outpost_ublc" ],
    "comment": "underground bottom left corner",
    "method": "json",
    "weight": 250,
    "object": {
      "fill_ter": "t_concrete_floor",
      "rows": [
        "######|l.....|  |...TTTT",
        "######|l.....|  |..cTTTT",
        "######|......|  |.......",
        "######|c.....|  --------",
        "######|TTT...+          ",
        "######|TTT...|          ",
        "#####-------------------",
        "#####|N.................",
        "#####|n...........1.....",
        "#####|n.................",
        "#####|n.................",
        "#####|n.................",
        "#####|............1.....",
        "#####|..................",
        "#####-------------------",
        "#################|      ",
        "#################|      ",
        "##------------###|  ----",
        "##|Hhh^...h..-----  |###",
        "##|H^huh.....+      |###",
        "##|Hh^.......+      |###",
        "##|^.h.^..h.^--------###",
        "##------------##########",
        "########################"
      ],
      "palettes": [ "mil_outpost_underground" ],
      "mapping": {
        "h": { "item": { "item": "corpse", "amount": [ 1, 4 ] }, "fields": { "field": "fd_blood" } },
        "H": { "item": { "item": "corpse", "amount": [ 3, 9 ] }, "fields": { "field": "fd_blood" } }
      },
      "place_fields": [ { "x": [ 2, 12 ], "y": [ 17, 22 ], "field": "fd_blood", "age": 2, "intensity": 2, "repeat": 20 } ]
    }
  }
]
