[
  {
    "type": "mapgen",
    "om_terrain": [ "mil_outpost_1te" ],
    "comment": "first floor top edge",
    "method": "json",
    "weight": 250,
    "object": {
      "fill_ter": "t_concrete_floor",
      "rows": [
        ",,,,,,,,,,,,,,,,,,,,,,,,",
        ",,,,,,,,,,,,,,,,,,,,,,,,",
        ",,,,,,,,,,,,,,,,,,,,,,,,",
        ",,,,,,,,,,,,,,,,,,,,,,,,",
        ",,,,,,,,,,,,,,,,,,,,,,,,",
        ",,,,,,,,,,,,,,,,,,,,,,,,",
        "------------------------",
        "------------------------",
        "..|                     ",
        "..+                     ",
        "..|  -------------------",
        ".n|  |c....>>...Db+_ _  ",
        ".n|  |b....>>...Db+_ _  ",
        "---  [bc........db------",
        "     [bb.....@@...|     ",
        "     |bb.....nnn..|     ",
        "-------------------  ---",
        "-------------------!!---",
        ",,,,,,,,,,,,,,,,,,,,,,,,",
        "wwwwwwwwwwwwwwwwwwwwwwww",
        "wwwwwwwwwwwwwwwwwwwwwwww",
        ",,,,,,,,,,,,,,,,,,,,,,,,",
        ",,,,,,,,,,,,,,,,,,,,,,,,",
        ",,,,,,,,,,,,,,,,,,,,,,,,"
      ],
      "palettes": [ "mil_outpost_bandit" ],
      "npcs": { "@": { "class": "thug" }, "z": { "class": "raider" } },
      "traps": { "_": "tr_bubblewrap" }
    }
  }
]
